AUTHORS.rst
HISTORY.rst
LICENSE
MANIFEST.in
README.rst
setup.cfg
setup.py
pyuwsgimemhog/__init__.py
pyuwsgimemhog/cli.py
pyuwsgimemhog/pyuwsgimemhog.py
pyuwsgimemhog.egg-info/PKG-INFO
pyuwsgimemhog.egg-info/SOURCES.txt
pyuwsgimemhog.egg-info/dependency_links.txt
pyuwsgimemhog.egg-info/entry_points.txt
pyuwsgimemhog.egg-info/not-zip-safe
pyuwsgimemhog.egg-info/requires.txt
pyuwsgimemhog.egg-info/top_level.txt
tests/test_pyuwsgimemhog.py