Metadata-Version: 1.1
Name: pyuwsgimemhog
Version: 0.2.0
Summary: uWSGI log parser to find memory hogs
Home-page: https://github.com/xrmx/pyuwsgimemhog
Author: Riccardo Magliocchetti
Author-email: riccardo.magliocchetti@gmail.com
License: MIT license
Keywords: pyuwsgimemhog
Platform: UNKNOWN
Classifier: Development Status :: 2 - Pre-Alpha
Classifier: Intended Audience :: Developers
Classifier: License :: OSI Approved :: MIT License
Classifier: Natural Language :: English
Classifier: Programming Language :: Python :: 3
Classifier: Programming Language :: Python :: 3.6
Classifier: Programming Language :: Python :: 3.7
Classifier: Programming Language :: Python :: 3.8
